phonikud_chatterbox/__init__.py
phonikud_chatterbox/py.typed
phonikud_chatterbox-0.1.0.dist-info/WHEEL
phonikud_chatterbox-0.1.0.dist-info/METADATA
phonikud_chatterbox-0.1.0.dist-info/RECORD
