Metadata-Version: 2.3
Name: phonikud-chatterbox
Version: 0.1.0
Summary: Add your description here
Author: thewh1teagle
Author-email: thewh1teagle <61390950+thewh1teagle@users.noreply.github.com>
Requires-Dist: chatterbox
Requires-Dist: phonikud>=0.4.1
Requires-Dist: phonikud-onnx>=1.0.6
Requires-Python: >=3.12
